eiabulk/__init__.py
eiabulk/eia_bulk.py
eiabulk/route_trees/og_route_tree.json
eiabulk/route_trees/og_short_route_tree.json
eiabulk/route_trees/updated_route_tree.json
eiabulk/route_trees/updated_short_route_tree.json
eia_bulk-0.1.1.dist-info/LICENSE
eia_bulk-0.1.1.dist-info/METADATA
eia_bulk-0.1.1.dist-info/WHEEL
eia_bulk-0.1.1.dist-info/top_level.txt
eia_bulk-0.1.1.dist-info/RECORD
