Metadata-Version: 2.1
Name: eia-bulk
Version: 0.1.1
Summary: EIA Bulk Data Collection package.
Author-email: CasFre4 <ocasfre@gmail.com>
Project-URL: Homepage, https://github.com/CasFre4/EIA-bulk
Project-URL: Issues, https://github.com/CasFre4/EIA-bulk/issues
Classifier: Programming Language :: Python :: 3
Classifier: License :: OSI Approved :: MIT License
Classifier: Operating System :: OS Independent
License-File: LICENSE
Requires-Dist: pandas==2.2.3
Requires-Dist: python-dotenv==1.0.1
Requires-Dist: python_dateutil==2.9.0.post0
Requires-Dist: Requests==2.32.3
Requires-Dist: SQLAlchemy==2.0.36
Requires-Dist: tenacity==9.0.0
